pynsta
