Metadata-Version: 1.0
Name: pynsta
Version: 0.11
Summary: A module for doing cool stuff with various websites, currently only operational for Instagram.
Home-page: https://github.com/HalfEmpty19/ArtiPy
Author: HalfEmpty
Author-email: halfemptynotfull@gmail.com
License: MIT
Platform: UNKNOWN
